[
  {
    "name": "Igor Castro",
    "workDays": [
      "monday",
      "tuesday",
      "wednesday",
      "thursday",
      "friday"
    ],
    "shiftStart": "12:00",
    "shiftEnd": "20:00",
    "weekendRotation": false,
    "active": true,
    "id": 1,
    "customSchedule": {
      "monday": {
        "start": "12:00",
        "end": "22:00"
      },
      "tuesday": {
        "start": "12:00",
        "end": "22:00"
      },
      "wednesday": {
        "start": "12:00",
        "end": "22:00"
      },
      "thursday": {
        "start": "12:00",
        "end": "22:00"
      },
      "friday": {
        "start": "13:00",
        "end": "22:00"
      }
    }
  },
  {
    "name": "Matheus Germano",
    "workDays": [
      "monday",
      "tuesday",
      "wednesday",
      "thursday",
      "friday"
    ],
    "shiftStart": "08:00",
    "shiftEnd": "18:00",
    "weekendRotation": false,
    "active": true,
    "id": 2,
    "customSchedule": {
      "friday": {
        "start": "08:00",
        "end": "17:00"
      },
      "thursday": {
        "start": "08:00",
        "end": "18:00"
      },
      "wednesday": {
        "start": "08:00",
        "end": "18:00"
      },
      "tuesday": {
        "start": "08:00",
        "end": "18:00"
      },
      "monday": {
        "start": "08:00",
        "end": "18:00"
      }
    }
  },
  {
    "name": "Alisson Rodrigo",
    "workDays": [
      "tuesday",
      "wednesday",
      "thursday",
      "friday",
      "monday"
    ],
    "shiftStart": "08:00",
    "shiftEnd": "12:00",
    "weekendRotation": false,
    "active": true,
    "id": 3,
    "customSchedule": {
      "monday": {
        "start": "08:00",
        "end": "18:00"
      },
      "tuesday": {
        "start": "08:00",
        "end": "18:00"
      },
      "wednesday": {
        "start": "08:00",
        "end": "18:00"
      },
      "thursday": {
        "start": "08:00",
        "end": "18:00"
      },
      "friday": {
        "start": "08:00",
        "end": "17:00"
      }
    }
  },
  {
    "name": "Kellen Cristina",
    "workDays": [
      "tuesday",
      "wednesday",
      "thursday",
      "friday",
      "saturday"
    ],
    "shiftStart": "12:00",
    "shiftEnd": "18:00",
    "weekendRotation": true,
    "active": true,
    "id": 4,
    "customSchedule": {
      "saturday": {
        "start": "08:00",
        "end": "17:00"
      },
      "tuesday": {
        "start": "09:00",
        "end": "19:00"
      },
      "wednesday": {
        "start": "09:00",
        "end": "19:00"
      },
      "thursday": {
        "start": "09:00",
        "end": "19:00"
      },
      "friday": {
        "start": "09:00",
        "end": "19:00"
      }
    }
  },
  {
    "name": "Kellen Silva",
    "workDays": [
      "saturday",
      "sunday"
    ],
    "shiftStart": "08:00",
    "shiftEnd": "18:00",
    "weekendRotation": true,
    "active": false,
    "id": 5
  },
  {
    "name": "Maicon Rocha",
    "workDays": [
      "saturday",
      "sunday"
    ],
    "shiftStart": "08:00",
    "shiftEnd": "18:00",
    "weekendRotation": true,
    "active": false,
    "id": 6
  },
  {
    "name": "Maicon Romano",
    "workDays": [
      "monday",
      "wednesday",
      "thursday",
      "tuesday",
      "sunday"
    ],
    "shiftStart": "08:00",
    "shiftEnd": "18:00",
    "weekendRotation": true,
    "active": true,
    "id": 7,
    "customSchedule": {
      "sunday": {
        "start": "08:00",
        "end": "17:00"
      },
      "monday": {
        "start": "08:00",
        "end": "18:00"
      },
      "tuesday": {
        "start": "08:00",
        "end": "18:00"
      },
      "wednesday": {
        "start": "08:00",
        "end": "18:00"
      },
      "thursday": {
        "start": "08:00",
        "end": "18:00"
      }
    }
  }
]